claimInsight/__init__.py
claimInsight/config.py
claimInsight/exceptions.py
claimInsight/extractor.py
claimInsight/prompts.py
claimInsight/utils.py
ClaimInsight-0.0.1.dist-info/METADATA
ClaimInsight-0.0.1.dist-info/WHEEL
ClaimInsight-0.0.1.dist-info/top_level.txt
ClaimInsight-0.0.1.dist-info/RECORD
