Metadata-Version: 2.1
Name: ClaimInsight
Version: 0.0.1
Summary: A library for extracting claims from various types of records
Home-page: https://github.com/mdarshad/ClaimInsight
Author: Mohd Arshad
Author-email: mdarshad1000@gmail.com
Classifier: Programming Language :: Python :: 3
Requires-Python: >=3.6
Requires-Dist: openai
Requires-Dist: python-dotenv
Requires-Dist: nltk
